pilgram/_1977.py
pilgram/__init__.py
pilgram/_version.py
pilgram/aden.py
pilgram/brannan.py
pilgram/brooklyn.py
pilgram/clarendon.py
pilgram/earlybird.py
pilgram/gingham.py
pilgram/hudson.py
pilgram/inkwell.py
pilgram/kelvin.py
pilgram/lark.py
pilgram/lofi.py
pilgram/maven.py
pilgram/mayfair.py
pilgram/moon.py
pilgram/nashville.py
pilgram/perpetua.py
pilgram/reyes.py
pilgram/rise.py
pilgram/slumber.py
pilgram/stinson.py
pilgram/toaster.py
pilgram/valencia.py
pilgram/walden.py
pilgram/willow.py
pilgram/xpro2.py
pilgram/css/__init__.py
pilgram/css/brightness.py
pilgram/css/contrast.py
pilgram/css/grayscale.py
pilgram/css/hue_rotate.py
pilgram/css/saturate.py
pilgram/css/sepia.py
pilgram/css/blending/__init__.py
pilgram/css/blending/alpha.py
pilgram/css/blending/color.py
pilgram/css/blending/color_burn.py
pilgram/css/blending/color_dodge.py
pilgram/css/blending/darken.py
pilgram/css/blending/difference.py
pilgram/css/blending/exclusion.py
pilgram/css/blending/hard_light.py
pilgram/css/blending/hue.py
pilgram/css/blending/lighten.py
pilgram/css/blending/multiply.py
pilgram/css/blending/nonseparable.py
pilgram/css/blending/normal.py
pilgram/css/blending/overlay.py
pilgram/css/blending/screen.py
pilgram/css/blending/soft_light.py
pilgram/css/blending/tests/helpers/__init__.py
pilgram/css/blending/tests/helpers/alpha_support.py
pilgram/util/__init__.py
pilgram/util/add.py
pilgram/util/apply_lut.py
pilgram/util/clip.py
pilgram/util/fill.py
pilgram/util/invert.py
pilgram/util/linear_gradient.py
pilgram/util/or_convert.py
pilgram/util/radial_gradient.py
pilgram/util/subtract.py
pilgram-1.2.1.data/data/screenshots/filter-performance-comparison.png
pilgram-1.2.1.data/data/screenshots/screenshot.png
pilgram-1.2.1.dist-info/LICENSE
pilgram-1.2.1.dist-info/METADATA
pilgram-1.2.1.dist-info/WHEEL
pilgram-1.2.1.dist-info/top_level.txt
pilgram-1.2.1.dist-info/RECORD
