Metadata-Version: 2.1
Name: pilgram
Version: 1.2.1
Summary: library for instagram filters
Home-page: https://github.com/akiomik/pilgram
Author: Akiomi Kamakura
Author-email: akiomik@gmail.com
License: Apache License 2.0
Keywords: pillow,instagram,instagram-filters,css-filters,image-blending,blend-modes,image-processing,data-augmentation
Platform: any
Classifier: License :: OSI Approved :: Apache Software License
Classifier: Operating System :: OS Independent
Classifier: Programming Language :: Python :: 3
Classifier: Programming Language :: Python :: 3.4
Classifier: Programming Language :: Python :: 3.5
Classifier: Programming Language :: Python :: 3.6
Classifier: Programming Language :: Python :: 3.7
Classifier: Programming Language :: Python :: 3.8
Classifier: Programming Language :: Python :: 3.9
Classifier: Programming Language :: Python :: 3.10
Classifier: Topic :: Multimedia :: Graphics
Classifier: Topic :: Software Development :: Libraries :: Python Modules
Requires-Python: !=3.0.*,!=3.1.*,!=3.2.*,!=3.3.*
License-File: LICENSE
Requires-Dist: numpy
